dongle/__dongle__.py
dongle/__init__.py
dongle/exceptions.py
dongle/lib/__init__.py
dongle/lib/primitives/__init__.py
dongle/lib/primitives/asymmetric_key.py
dongle/lib/primitives/kdf.py
dongle/lib/primitives/password.py
dongle/lib/primitives/symmetric_key.py
dongle/lib/protocol/__init__.py
dongle/lib/protocol/encryption.py
dongle/lib/protocol/key_derivation.py
dongle/lib/protocol/signing.py
dongle/runtime/__init__.py
dongle/runtime/bootstrap.py
dongle/runtime/keyring.py
dongle/runtime/license.py
dongle/runtime/runtime_hooks.py
dongle/runtime/supervisor.py
dongle/runtime/formats/__init__.py
dongle/runtime/formats/ascii_armor.py
dongle/runtime/formats/encrypted_module.py
dongle/runtime/formats/signed_module.py
dongle/runtime/machinery/__init__.py
dongle/runtime/machinery/exceptions.py
dongle/runtime/machinery/finder.py
dongle/runtime/machinery/loader.py
dongle/runtime/machinery/util.py
dongle/util/__init__.py
dongle/util/__main__.py
dongle/util/check.py
dongle/util/cli.py
dongle/util/commands.py
dongle_core-0.1.0.dev1.dist-info/licenses/LICENSES/Apache-2.0.txt
dongle_core-0.1.0.dev1.dist-info/licenses/LICENSES/CC-BY-SA-4.0.txt
dongle_core-0.1.0.dev1.dist-info/licenses/LICENSES/CC0-1.0.txt
dongle_core-0.1.0.dev1.dist-info/METADATA
dongle_core-0.1.0.dev1.dist-info/WHEEL
dongle_core-0.1.0.dev1.dist-info/entry_points.txt
dongle_core-0.1.0.dev1.dist-info/top_level.txt
dongle_core-0.1.0.dev1.dist-info/RECORD
