Metadata-Version: 2.4
Name: dongle-core
Version: 0.1.0.dev1
Summary: Python license manager (core runtime)
Author-email: Michael Meinel <led02@me.com>
License-Expression: Apache-2.0
Project-URL: Homepage, https://www.led-inc.eu/dongle
Project-URL: Repository, https://github.com/led02/dongle.git
Classifier: Programming Language :: Python :: 3
Classifier: Operating System :: OS Independent
Requires-Python: >=3.11
License-File: LICENSES/Apache-2.0.txt
License-File: LICENSES/CC-BY-SA-4.0.txt
License-File: LICENSES/CC0-1.0.txt
Requires-Dist: cryptography
Dynamic: license-file
